[1,["50a75f84-2cee-4ecf-84ff-934477ed306c","84a0b865-0275-47fc-9fe4-0f03925a316c@f9941","12ccf59e-15a4-40a5-9329-f335cd75f07f@6c48a","1fa42dfd-b7ac-4791-9812-7f1cf6b3f701@6c48a","1fa42dfd-b7ac-4791-9812-7f1cf6b3f701@f9941","a0aac948-c985-4fc0-8214-e6111c245e39@f9941","fa2fc54b-f117-41b2-ac1d-b17592dc1061@f9941","12ccf59e-15a4-40a5-9329-f335cd75f07f@f9941","f6d6e1e6-879c-4bd3-9942-f11ea80709c5@f9941","84a0b865-0275-47fc-9fe4-0f03925a316c@6c48a","f6d6e1e6-879c-4bd3-9942-f11ea80709c5@6c48a","fa2fc54b-f117-41b2-ac1d-b17592dc1061@6c48a"],["node","_textureSource","_spriteFrame","_font","root","resources","addCount","count","allCount","border","title","icon","coloredBg","_target","target","data","_parent","startSprite","endSprite"],[["cc.Widget",["_alignFlags","_originalHeight","_originalWidth","_right","_bottom","_left","_top","node","__prefab","_target"],-4,1,4,1],["cc.Node",["_name","_layer","_active","_components","_prefab","_parent","_children","_lpos"],0,9,4,1,2,5],"cc.SpriteFrame",["cc.Sprite",["_type","_sizeMode","_isTrimmedMode","node","__prefab","_spriteFrame","_color"],0,1,4,6,5],["cc.Node",["_name","_layer","_active","_parent","_components","_prefab","_lpos","_children"],0,1,12,4,5,2],["cc.Layout",["_layoutType","_resizeMode","_paddingTop","_paddingBottom","_spacingY","_paddingLeft","_paddingRight","_spacingX","_isAlign","node","__prefab"],-6,1,4],["cc.Prefab",["_name"],2],["cc.UITransform",["node","__prefab","_contentSize"],3,1,4,5],["cc.CompPrefabInfo",["fileId"],2],["4d13doGp95Fmrtire4TB7la",["building","node","__prefab","coloredBg","icon","title","border","allCount","count","addCount","resources"],2,1,4,1,1,1,1,1,1,1,1],["cc.Button",["_transition","_zoomScale","node","__prefab","clickEvents","_target"],1,1,4,9,1],["cc.ClickEvent",["_componentId","handler","target"],1,1],["cc.PrefabInfo",["fileId","instance","targetOverrides","nestedPrefabInstanceRoots","root","asset"],-1,1,1],["cc.Mask",["_type","node","__prefab"],2,1,4],["4489bY5gZVNGrIZkUi5M7ZU",["node","__prefab","color","startSprite","endSprite"],3,1,4,5,6,6],["32daaQ63V1AqZ1vS/qU7Wuq",["_string","_actualFontSize","_fontSize","_lineHeight","_isSystemFontUsed","node","__prefab","_color"],-2,1,4,5],["9950cXlk+NHPbkzuDlrJGsu",["node","__prefab"],3,1,4],["cc.Label",["_string","_actualFontSize","_fontSize","_lineHeight","_enableWrapText","_isSystemFontUsed","node","__prefab","_color"],-3,1,4,5],["cc.TTFFont",["_name","_native"],1]],[[8,0,2],[7,0,1,2,1],[12,0,1,2,3,4,5,5],[4,0,1,3,4,5,3],[0,0,2,1,7,8,4],[17,0,1,2,3,4,5,6,7,8,7],[1,0,1,5,6,3,4,3],[1,0,1,5,3,4,3],[3,0,1,3,4,6,5,3],[6,0,2],[1,0,1,6,3,4,3],[1,0,1,6,3,4,7,3],[1,0,1,5,3,4,7,3],[1,0,2,1,5,3,4,4],[1,0,1,5,6,3,4,7,3],[4,0,2,1,3,7,4,5,6,4],[4,0,1,3,4,5,6,3],[9,0,1,2,3,4,5,6,7,8,9,10,2],[10,0,1,2,3,4,5,3],[11,0,1,2,3],[13,0,1,2,2],[3,0,1,2,3,4,5,4],[3,0,1,2,3,4,6,5,4],[3,0,1,2,3,4,6,4],[0,0,3,4,1,7,8,5],[0,0,5,3,2,1,7,8,6],[0,0,1,7,8,3],[0,0,4,2,7,8,4],[0,0,2,7,8,3],[0,0,7,8,2],[0,0,5,3,6,4,2,1,7,8,8],[0,0,5,3,2,1,7,8,9,6],[5,0,2,3,4,9,10,5],[5,1,0,9,10,3],[5,1,0,5,6,7,8,9,10,7],[14,0,1,2,3,4,1],[15,0,1,2,3,4,5,6,7,6],[16,0,1,1],[18,0,1,3]],[[[{"name":"BgPixel","rect":{"x":0,"y":0,"width":1,"height":1},"offset":{"x":0,"y":0},"originalSize":{"width":1,"height":1},"rotated":false,"capInsets":[0,0,0,0],"vertices":{"rawPosition":[-0.5,-0.5,0,0.5,-0.5,0,-0.5,0.5,0,0.5,0.5,0],"indexes":[0,1,2,2,1,3],"uv":[0,1,1,1,0,0,1,0],"nuv":[0,0,1,0,0,1,1,1],"minPos":{"x":-0.5,"y":-0.5,"z":0},"maxPos":{"x":0.5,"y":0.5,"z":0}},"packable":true,"pixelsToUnit":100,"pivot":{"x":0.5,"y":0.5},"meshType":0}],[2],0,[0],[1],[2]],[[{"name":"Border_24","rect":{"x":0,"y":0,"width":100,"height":100},"offset":{"x":0,"y":0},"originalSize":{"width":100,"height":100},"rotated":false,"capInsets":[40,40,40,40],"vertices":{"rawPosition":[-50,-50,0,50,-50,0,-50,50,0,50,50,0],"indexes":[0,1,2,2,1,3],"uv":[0,100,100,100,0,0,100,0],"nuv":[0,0,1,0,0,1,1,1],"minPos":{"x":-50,"y":-50,"z":0},"maxPos":{"x":50,"y":50,"z":0}},"packable":true,"pixelsToUnit":100,"pivot":{"x":0.5,"y":0.5},"meshType":0}],[2],0,[0],[1],[3]],[[[9,"BuildCard"],[10,"BuildCard",33554432,[-15,-16,-17,-18],[[1,-2,[0,"c5gCd/KiJIBJr4r4gyFy2o"],[5,192,228]],[17,0,-11,[0,"b9JpGqZzxM4a+O/+xDHS0v"],-10,-9,-8,-7,-6,-5,-4,-3],[18,3,0.96,-14,[0,"f7etAiyKxPVqBhW8MbFK69"],[[19,"4d13doGp95Fmrtire4TB7la","onCardClick",-13]],-12]],[2,"a5ii+AZ0lOeYXBRSNe6Twz",null,null,null,-1,0]],[11,"BuildCardWrapper",33554432,[-22,-23,-24],[[1,-19,[0,"c6jz1/8jxNKKBAwyBnvR5V"],[5,176,176]],[20,3,-20,[0,"5eLWIhYvFMVLity4paHNfP"]],[21,1,0,false,-21,[0,"1bsjg2ySpEAaaLPMdzOFOR"],4]],[2,"49KedgFWdHpLC8QWIK5HrU",null,null,null,1,0],[1,0,-18,0]],[15,"BuildCardInfo",false,33554432,2,[-28,-29],[[[1,-25,[0,"497De8Gi9KOYKZWqYz4x9p"],[5,12,32.004]],[24,33,8,4,32,-26,[0,"fcd01+IHJNbLblNDIq0eTE"]],-27],4,4,1],[2,"4dLSLr4RlONIdEBThRi83U",null,null,null,1,0],[1,74,71.998,0]],[6,"BuildCardContent",33554432,1,[-33,2],[[1,-30,[0,"f4/TdgnMNI7p+y6IVRNemA"],[5,176,228]],[32,2,8,8,4,-31,[0,"fdMvr1cLdHnYAXDTOhNcrH"]],[25,45,8,8,100,100,-32,[0,"8ayfmM3QtCtKF3d919K8LX"]]],[2,"12munLg6hMua4y21T+mssj",null,null,null,1,0]],[6,"BuildCardInfoWrapper",33554432,3,[-37,-38],[[1,-34,[0,"6b310pkA1CS7DlnC6P6EUS"],[5,12,32.004]],[33,1,1,-35,[0,"c4NMsFw1VGfI2jy7s3Mb54"]],[26,5,32,-36,[0,"2ew4fIppJOqrOTxcHmTyZA"]]],[2,"efX1V5nxlJLpg7O1WFmL/Y",null,null,null,1,0]],[12,"BuildCardResources",33554432,1,[[1,-39,[0,"c3Vldmja1Iu6/Fi8Kb5jCt"],[5,28,32]],[27,20,-16,100,-40,[0,"562EuDMB5KgZfO66ye8RaF"]],[34,1,1,16,16,4,true,-41,[0,"e9El7FNa5CFYC8mO+jOjkW"]],[8,1,0,-42,[0,"8a3WG/0wpLe4xkBd8WefPZ"],[4,4293653995],5]],[2,"bei5bkwhpMWLRaAYiUqXEg",null,null,null,1,0],[1,0,-114,0]],[13,"BuildCardBorder",false,33554432,1,[[1,-43,[0,"259xHtjmlDn6Z2W0L/mBEM"],[5,200,236]],[4,45,100,100,-44,[0,"3dGvPzLY9Ks7SOqgmYd1ON"]],[8,1,0,-45,[0,"76pRJElWFJzYuBTq/qfj6X"],[4,4294739249],0]],[2,"c9JCBA9gdLK5ytGAJDGkgE",null,null,null,1,0]],[7,"BuildCardBg",33554432,1,[[1,-46,[0,"f5ZLBqDZtNeoS3+3E2jHzW"],[5,192,228]],[22,1,0,false,-47,[0,"b1+z+FKmhF6rEjjn3aiNpG"],[4,858989344],1],[4,45,192,228,-48,[0,"a4DVYAJxVA9IAK2GbQqJaZ"]]],[2,"8ctKS8++JPK6gyW0I2ICuD",null,null,null,1,0]],[14,"BuildCardTitleWrapper",33554432,4,[-51],[[1,-49,[0,"946wQ62tREvYfCiqZOPSYt"],[5,176,32]],[28,40,100,-50,[0,"46HMsOJ0VNZKjW/DDHNJh5"]]],[2,"26eqf4eZJLZYOqswl1pswE",null,null,null,1,0],[1,0,90,0]],[3,"BuildCardTitle",33554432,9,[[[1,-52,[0,"48gect34BElrI5FK9E0CEp"],[5,0,30.240000000000002]],[29,18,-53,[0,"83xEaAyGVG3b9jU0BcWBwZ"]],-54],4,4,1],[2,"d82WQAGJ1Jqq441jfqDcOC",null,null,null,1,0]],[3,"BuildCardWrapperBg",33554432,2,[[[1,-55,[0,"99mRZeAFlLWKW8ujyFTvbj"],[5,176,176]],[4,45,176,176,-56,[0,"d4Hc8cWAlOEZ7BXgAvDAaB"]],-57],4,4,1],[2,"f4LvZMbnBDOowWs7j/uOxT",null,null,null,1,0]],[3,"BuildCardIcon",33554432,2,[[[1,-58,[0,"c6CmXI6sVL2oKP8ZCY9XBH"],[5,160,160]],[30,45,8,8,8,8,160,160,-59,[0,"52yn/XqQpKn4/224JrDFEp"]],-60],4,4,1],[2,"8cp1oWb+5BhLWDG9BGcVOX",null,null,null,1,0]],[7,"BuildCardInfoBg",33554432,3,[[1,-61,[0,"7b3XmNYiJMNbv+/yhZX5zV"],[5,28,32.004]],[31,45,-8,-8,100,100,-62,[0,"b53viduv5Jiqf1ygid4At6"],3],[35,-63,[0,"39nFRigBpBZLCIhUcuyJ/S"],[4,4281541408],2,3]],[2,"d1Yw8L3oRHiIwnXBvfrEZE",null,null,null,1,0]],[3,"BuildCardInfoCount",33554432,5,[[[1,-64,[0,"d25+bSpQNDW781w0NyyKNA"],[5,12,32.004]],-65],4,1],[2,"3bffVKquRP75iaWUhLoQGF",null,null,null,1,0]],[16,"BuildCardInfoAddCount",33554432,5,[[[1,-66,[0,"bc7ZYwngxA44EIgALz7GlB"],[5,24,32.004]],-67],4,1],[2,"35btEF+mFAp4/Z9szComci",null,null,null,1,0],[1,6,0,0]],[36,"",24,24,24,false,10,[0,"5fn2V58k5JbaEBwSJ2LS+q"],[4,4281541408]],[23,1,0,false,11,[0,"d3SWgdqhlHaJGcP9SFJR2s"],[4,2139730133]],[37,12,[0,"a9JLv5SXBMT7nDLniDYdfk"]],[5,"",20,20,25.4,false,false,14,[0,"cbnaerWmxMeqKfHQ5e+VLM"],[4,4293653995]],[5,"+1",20,20,25.4,false,false,15,[0,"44d+w8ZbJJsoLtak8rvgED"],[4,4294739249]],[5,"+1",20,20,25.4,false,false,3,[0,"b0nY+bRxdDvYwDAoeRgGIA"],[4,4293653995]]],0,[0,4,1,0,0,1,0,5,6,0,6,20,0,7,19,0,8,21,0,9,7,0,10,16,0,11,18,0,12,17,0,0,1,0,13,1,0,14,1,0,0,1,0,-1,7,0,-2,8,0,-3,4,0,-4,6,0,0,2,0,0,2,0,0,2,0,-1,11,0,-2,12,0,-3,3,0,0,3,0,0,3,0,-3,21,0,-1,13,0,-2,5,0,0,4,0,0,4,0,0,4,0,-1,9,0,0,5,0,0,5,0,0,5,0,-1,14,0,-2,15,0,0,6,0,0,6,0,0,6,0,0,6,0,0,7,0,0,7,0,0,7,0,0,8,0,0,8,0,0,8,0,0,9,0,0,9,0,-1,10,0,0,10,0,0,10,0,-3,16,0,0,11,0,0,11,0,-3,17,0,0,12,0,0,12,0,-3,18,0,0,13,0,0,13,0,0,13,0,0,14,0,-2,19,0,0,15,0,-2,20,0,15,1,2,16,4,67],[0,0,0,0,0,0,16,17,19,20,21],[2,2,17,18,2,2,3,2,3,3,3],[4,5,6,7,1,8,0,1,0,0,0]],[[[38,"Nunito-Bold","Nunito-Bold.ttf"],-1],0,0,[],[],[]],[[{"name":"Bg_20","rect":{"x":0,"y":0,"width":100,"height":100},"offset":{"x":0,"y":0},"originalSize":{"width":100,"height":100},"rotated":false,"capInsets":[40,40,40,40],"vertices":{"rawPosition":[-50,-50,0,50,-50,0,-50,50,0,50,50,0],"indexes":[0,1,2,2,1,3],"uv":[0,100,100,100,0,0,100,0],"nuv":[0,0,1,0,0,1,1,1],"minPos":{"x":-50,"y":-50,"z":0},"maxPos":{"x":50,"y":50,"z":0}},"packable":true,"pixelsToUnit":100,"pivot":{"x":0.5,"y":0.5},"meshType":0}],[2],0,[0],[1],[9]],[[{"name":"BgCount","rect":{"x":1,"y":0,"width":62,"height":32},"offset":{"x":0,"y":0},"originalSize":{"width":64,"height":32},"rotated":false,"capInsets":[16,8,16,8],"vertices":{"rawPosition":[-31,-16,0,31,-16,0,-31,16,0,31,16,0],"indexes":[0,1,2,2,1,3],"uv":[1,32,63,32,1,0,63,0],"nuv":[0.015625,0,0.984375,0,0.015625,1,0.984375,1],"minPos":{"x":-31,"y":-16,"z":0},"maxPos":{"x":31,"y":16,"z":0}},"packable":true,"pixelsToUnit":100,"pivot":{"x":0.5,"y":0.5},"meshType":0}],[2],0,[0],[1],[10]],[[{"name":"BuildCardInfoLeftBg","rect":{"x":0,"y":0,"width":16,"height":32},"offset":{"x":0,"y":0},"originalSize":{"width":16,"height":32},"rotated":false,"capInsets":[0,0,0,0],"vertices":{"rawPosition":[-8,-16,0,8,-16,0,-8,16,0,8,16,0],"indexes":[0,1,2,2,1,3],"uv":[0,32,16,32,0,0,16,0],"nuv":[0,0,1,0,0,1,1,1],"minPos":{"x":-8,"y":-16,"z":0},"maxPos":{"x":8,"y":16,"z":0}},"packable":true,"pixelsToUnit":100,"pivot":{"x":0.5,"y":0.5},"meshType":0}],[2],0,[0],[1],[11]]]]
